{
	"category" : "GitHub-Repositories",
	"classinstvars" : [
		 ],
	"classvars" : [
		 ],
	"commentStamp" : "SkipLentz 10/9/2015 11:01",
	"instvars" : [
		"forks_url",
		"contents_url",
		"assignees_url",
		"subscription_url",
		"releases_url",
		"contributors_url",
		"events_url",
		"issues_url",
		"full_name",
		"tags_url",
		"archive_url",
		"owner",
		"git_refs_url",
		"commits_url",
		"size",
		"watchers_count",
		"pulls_url",
		"stargazers_count",
		"labels_url",
		"keys_url",
		"git_url",
		"watchers",
		"fork",
		"name",
		"trees_url",
		"teams_url",
		"notifications_url",
		"ssh_url",
		"svn_url",
		"language",
		"git_tags_url",
		"collaborators_url",
		"forks",
		"subscribers_url",
		"clone_url",
		"private",
		"branches_url",
		"has_pages",
		"mirror_url",
		"compare_url",
		"issue_events_url",
		"downloads_url",
		"hooks_url",
		"has_downloads",
		"has_wiki",
		"forks_count",
		"blobs_url",
		"issue_comment_url",
		"description",
		"html_url",
		"open_issues",
		"default_branch",
		"statuses_url",
		"milestones_url",
		"permissions",
		"stargazers_url",
		"open_issues_count",
		"organization",
		"has_issues",
		"languages_url",
		"network_count",
		"git_commits_url",
		"homepage",
		"pushed_at",
		"merges_url",
		"comments_url" ],
	"name" : "GHRepository",
	"pools" : [
		 ],
	"super" : "GHObject",
	"type" : "normal" }
