{
	"class" : {
		"openOnRepository:" : "Balletie 11/25/2015 13:53:52",
		"specLayout" : "Balletie 11/25/2015 13:53:52",
		"title" : "Balletie 11/25/2015 13:53:52" },
	"instance" : {
		"branch" : "Balletie 11/25/2015 13:53:52",
		"branch:" : "Balletie 11/25/2015 13:53:52",
		"branchName" : "Balletie 11/25/2015 13:53:52",
		"iconForItem:" : "Balletie 11/25/2015 13:53:52",
		"info" : "Balletie 11/25/2015 13:53:52",
		"initialExtent" : "Balletie 11/25/2015 13:53:52",
		"initialize" : "Balletie 11/25/2015 13:53:52",
		"initializeHiedra" : "Balletie 11/25/2015 13:53:52",
		"initializePresenter" : "Balletie 11/25/2015 13:53:52",
		"initializeWidgets" : "Balletie 11/25/2015 13:53:52",
		"isItemLoaded:" : "Balletie 11/25/2015 13:53:52",
		"log" : "Balletie 11/25/2015 13:53:52",
		"packageList" : "Balletie 11/25/2015 13:53:52",
		"repository" : "Balletie 11/25/2015 13:53:52",
		"repository:" : "Balletie 11/25/2015 13:53:52",
		"sortedLogItems" : "Balletie 11/25/2015 13:53:52",
		"stringForTime:" : "Balletie 11/25/2015 13:53:52" } }
